conducto/__init__.py
conducto/__main__.py
conducto/_version.py
conducto/callback.py
conducto/conducto_notebook.py
conducto/data.py
conducto/debug.py
conducto/git.py
conducto/pipeline.py
conducto/profile.py
conducto/schedule.py
conducto/slack.py
conducto/util.py
conducto/api/__init__.py
conducto/api/analytics.py
conducto/api/api_utils.py
conducto/api/auth.py
conducto/api/config.py
conducto/api/dir.py
conducto/api/manager.py
conducto/api/misc.py
conducto/api/pipeline.py
conducto/api/secrets.py
conducto/contrib/__init__.py
conducto/contrib/discover/__init__.py
conducto/contrib/discover/cli.py
conducto/contrib/discover/codegen.py
conducto/contrib/discover/treegen.py
conducto/glue/__init__.py
conducto/glue/arg.py
conducto/glue/method.py
conducto/image/__init__.py
conducto/image/cleanup.py
conducto/image/dockerfile.py
conducto/image/internal_image.py
conducto/image/names.py
conducto/image/stdout_handler.py
conducto/integrations/__init__.py
conducto/integrations/git.py
conducto/integrations/slack.py
conducto/internal/__init__.py
conducto/internal/build.py
conducto/internal/host_detection.py
conducto/nb/__init__.py
conducto/nb/backend_matplotlib.py
conducto/nb/conducto_notebook.py
conducto/nb/magic.py
conducto/shared/__init__.py
conducto/shared/agent_utils.py
conducto/shared/async_backport.py
conducto/shared/async_utils.py
conducto/shared/chunker.py
conducto/shared/client_utils.py
conducto/shared/constants.py
conducto/shared/container_utils.py
conducto/shared/data.py
conducto/shared/exceptions.py
conducto/shared/github_utils.py
conducto/shared/imagepath.py
conducto/shared/kwarg_exception.py
conducto/shared/log.py
conducto/shared/parse_utils.py
conducto/shared/path_utils.py
conducto/shared/request_utils.py
conducto/shared/reservations.py
conducto/shared/resource_validation.py
conducto/shared/termsize.py
conducto/shared/types.py
conducto/shell_ui/__init__.py
conducto/shell_ui/full_screen.py
conducto/shell_ui/one_line.py
conducto/tutorials/__init__.py
conducto-0.1.28.dist-info/METADATA
conducto-0.1.28.dist-info/WHEEL
conducto-0.1.28.dist-info/entry_points.txt
conducto-0.1.28.dist-info/top_level.txt
conducto-0.1.28.dist-info/RECORD
