Metadata-Version: 2.1
Name: conducto
Version: 0.1.28
Summary: Pipeline orchestration and execution
Home-page: https://www.conducto.com
Author: conducto
Author-email: beta@conducto.com
License: Apache-2.0
Project-URL: Code, https://github.com/conducto/conducto
Platform: UNKNOWN
Classifier: Programming Language :: Python :: 3
Classifier: License :: OSI Approved :: Apache Software License
Classifier: Operating System :: OS Independent
Requires-Python: >=3.6.1
Requires-Dist: python-dateutil
Requires-Dist: python-jose
Requires-Dist: boto3
Requires-Dist: websockets
Requires-Dist: packaging
Requires-Dist: ansiwrap
Requires-Dist: rich
Requires-Dist: astsearch
Requires-Dist: colorama ; platform_system == "Windows"
Requires-Dist: pywin32 (>=1.0) ; platform_system == "Windows"
